ansible_merge_vars.py
ansible_merge_vars-5.0.0.dist-info/LICENSE.md
ansible_merge_vars-5.0.0.dist-info/METADATA
ansible_merge_vars-5.0.0.dist-info/WHEEL
ansible_merge_vars-5.0.0.dist-info/top_level.txt
ansible_merge_vars-5.0.0.dist-info/RECORD
