Metadata-Version: 2.1
Name: ansible-merge-vars
Version: 5.0.0
Summary: An Ansible action plugin to explicitly merge inventory variables
Home-page: https://github.com/leapfrogonline/ansible-merge-vars
Author: Leapfrog Online
Author-email: dfuchs@leapfrogonline.com
License: UNKNOWN
Project-URL: Bug Reports, https://github.com/leapfrogonline/ansible-merge-vars/issues
Project-URL: Source, https://github.com/leapfrogonline/ansible-merge-vars/
Keywords: ansible plugin
Platform: UNKNOWN
Classifier: Development Status :: 5 - Production/Stable
Classifier: Intended Audience :: Developers
Classifier: Topic :: System :: Systems Administration
Classifier: License :: OSI Approved :: Apache Software License
Classifier: Programming Language :: Python :: 2.7
Classifier: Programming Language :: Python :: 3.5
Classifier: Programming Language :: Python :: 3.6
Classifier: Programming Language :: Python :: 3.7
Classifier: Programming Language :: Python :: 3.8
